schains/__init__.py
schains/chains.py
schains/tsmodels.py
seasonality_chains-0.2.0.dist-info/LICENSE
seasonality_chains-0.2.0.dist-info/METADATA
seasonality_chains-0.2.0.dist-info/WHEEL
seasonality_chains-0.2.0.dist-info/top_level.txt
seasonality_chains-0.2.0.dist-info/RECORD
