Metadata-Version: 2.1
Name: seasonality-chains
Version: 0.2.0
Summary: A framework for forecasting time-series with multiple seasonal components
Home-page: https://github.com/andrewargatkiny/seasonality-chains
Author: Andrew Argatkiny
Author-email: andrewkrskde@gmail.com
License: UNKNOWN
Keywords: time series,forecast,predict,analysisseasonality,statistics,econometrics
Platform: UNKNOWN
Classifier: Development Status :: 3 - Alpha
Classifier: License :: OSI Approved :: BSD License
Classifier: Programming Language :: Python :: 3
Classifier: Programming Language :: Python :: 3.6
Classifier: Programming Language :: Python :: 3.7
Classifier: Programming Language :: Python :: 3.8
Classifier: Programming Language :: Python :: 3.9
Classifier: Programming Language :: Python :: 3 :: Only
Classifier: Operating System :: OS Independent
Classifier: Topic :: Scientific/Engineering
Classifier: Topic :: Scientific/Engineering :: Information Analysis
Requires-Python: >=3.6
License-File: LICENSE
Requires-Dist: pandas
Requires-Dist: numpy
Requires-Dist: scikit-learn
